Metadata-Version: 2.1
Name: ctc_forced_aligner
Version: 1.0.1
Summary: CTC Forced Alignment
Author: Deskpai
Author-email: dev@deskpai.com
Requires-Dist: requests>=2.32.3
Requires-Dist: librosa>=0.10.2.post1
Requires-Dist: numpy==1.26.3
Requires-Dist: onnxruntime>=1.20.1
